[
  {
    "raceId": "1ctvjkyfefmodyagz97s25n1fxoqk1mw",
    "racerId": "5f7d0ee7c0ee0e0e0e0e0e0",
    "raceName": "Sprint 2",
    "raceDate": "2022-07-19T00:00:00.000Z",
    "raceTime": "2022-07-19T00:00:00.000Z",
    "raceLocation": "Sprint 2",
    "raceType": "Sprint",
    "raceDistance": 1000,
    "raceTrack": "Sprint 2",
    "raceTrackType": "Sprint"
  },
  {
    "raceId": "1ctvjkyfefmodyagz97s25n1fxoqk1mw",
    "racerId": "2h6jd7djg3n2ivsj3n2",
    "raceName": "Tester 1",
    "raceDate": "2022-07-19T00:00:00.000Z",
    "raceTime": "2022-07-19T00:00:00.000Z",
    "raceLocation": "Sprint 2",
    "raceType": "Sprint"
  },
  {
    "raceId": "1ctvjkyfefmodyagz97s25n1fxoqk1",
    "racerId": "26nwjv882jn989cn2jvisid",
    "raceName": "Tester2",
    "raceDate": "2022-07-19T00:00:00.000Z"
  }
]